Metadata-Version: 1.0
Name: sdistributions
Version: 0.1
Summary: Gaussian and Binomial distributions
Home-page: UNKNOWN
Author: Udacity AWS course
Author-email: UNKNOWN
License: UNKNOWN
Platform: UNKNOWN
